ELEC374_Tutorial/Bus.v
module Bus (
    input [7:0] BusMuxInRZ, 
    input [7:0] BusMuxInRA, 
    input [7:0] BusMuxInRB,
    input RZout, RAout, RBout,
    output wire [7:0] BusMuxOut
);

    reg [7:0] q;

    always @ (*) begin
        if(RZout) q = BusMuxInRZ;
        else if(RAout) q = BusMuxInRA;
        else if(RBout) q = BusMuxInRB;
    end

    assign BusMuxOut = q;
endmodule

ELEC374_Tutorial/register.v
module register #(parameter DATA_WIDTH_IN = 8, DATA_WIDTH_OUT = 8, INIT = 8'h0)(
    input clear, clock, enable,
    input [DATA_WIDTH_IN-1:0] BusMuxOut,
    output wire [DATA_WIDTH_OUT-1:0] BusMuxIn
);
    reg [DATA_WIDTH_IN-1:0] q;
    initial q = INIT;

    always @ (posedge clock)
    begin
        if (clear) begin
            q <= {DATA_WIDTH_IN{1'b0}};
        end
        else if (enable) begin
            q <= BusMuxOut;
        end
    end
    assign BusMuxIn = q[DATA_WIDTH_OUT-1:0];
endmodule

ELEC374_Tutorial/adder.v
module adder(A, B, Result);
    input [7:0] A, B;
    output [7:0] Result;

    reg [7:0] Result;
    reg [8:0] LocalCarry;

    integer i;

    always@(A or B)
    begin
        LocalCarry = 9'd0;
        for(i = 0; i < 8; i = i + 1)
        begin
            Result[i] = A[i]^B[i]^LocalCarry[i];
            LocalCarry[i+1] = (A[i]&B[i])|(LocalCarry[i]&(A[i]|B[i]));
        end
    end
endmodule

ELEC374_Tutorial/DataPath.v
module DataPath(
    input wire clock, clear,
    input wire [7:0] A,
    input wire [7:0] RegisterAImmediate,
    input wire RZout, RAout, RBout,
    input wire RAin, RBin, RZin
);

    wire [7:0] BusMuxOut, BusMuxInRZ, BusMuxInRA, BusMuxInRB;
    wire [7:0] Zregin;

    // Devices
    register RA(clear, clock, RAin, RegisterAImmediate, BusMuxInRA);
    register RB(clear, clock, RBin, BusMuxOut, BusMuxInRB);

    // Adder
    adder add(A, BusMuxOut, Zregin);
    register RZ(clear, clock, RZin, Zregin, BusMuxInRZ);

    // Bus
    Bus bus(BusMuxInRZ, BusMuxInRA, BusMuxInRB, RZout, RAout, RBout, BusMuxOut);

endmodule

ELEC374_Tutorial/tutorial_tb.v
`timescale 1ns/10ps

module tutorial_tb();
    reg clock, clear, RZout, RAout, RBout, RAin, RBin, RZin;
    reg [7:0] AddImmediate;
    reg [7:0] RegisterAImmediate;

    reg [3:0] present_state;

    // Instantiating the DataPath
    DataPath DP(
        clock, clear,
        AddImmediate,
        RegisterAImmediate,
        RZout, RAout, RBout,
        RAin, RBin, RZin
    );

    parameter init = 4'd1, T0 = 4'd2, T1 = 4'd3, T2 = 4'd4;

    initial begin clock = 0; present_state = 4'd1; end
    always #10 clock = ~clock;
    always @(negedge clock) present_state = present_state + 1;

    always @(present_state) begin
        case(present_state)
            init: begin
                clear <= 1;
                AddImmediate <= 8'h00; RegisterAImmediate <= 8'h00;
                RZout <= 0; RAout <= 0; RBout <= 0; RAin <= 0; RBin <= 0; RZin <= 0;
                #15 clear <= 0;
            end
            // ldi A, 5
            T0: begin
                RegisterAImmediate <= 8'h5; RAin <= 1;
                #15 RegisterAImmediate <= 8'h00; RAin <= 0;
            end
            // addi B, A, 5 - 2 steps
            // add value in register A and immediate 5 and then save in Z
            T1: begin
                RAout <= 1; AddImmediate <= 8'h5; RZin <= 1;
                #15 RAout <= 0; RZin <= 0;
            end
            // mv B, Z - move value in Z to B
            T2: begin
                RZout <= 1; RBin <= 1;
                #15 RZout <= 0; RBin <= 0;
            end
        endcase
    end

    initial begin
        $dumpfile("tutorial_tb.vcd");
        $dumpvars;
        #80;
        $display("Simulation complete.");
        $finish;
    end
endmodule

ELEC374_Tutorial/tutorial_tb.vcd
$date
	Mon Feb  2 15:59:52 2026
$end
$version
	Icarus Verilog
$end
$timescale
	10ps
$end
$scope module tutorial_tb $end
$var parameter 4 ! T0 $end
$var parameter 4 " T1 $end
$var parameter 4 # T2 $end
$var parameter 4 $ init $end
$var reg 8 % AddImmediate [7:0] $end
$var reg 1 & RAin $end
$var reg 1 ' RAout $end
$var reg 1 ( RBin $end
$var reg 1 ) RBout $end
$var reg 1 * RZin $end
$var reg 1 + RZout $end
$var reg 8 , RegisterAImmediate [7:0] $end
$var reg 1 - clear $end
$var reg 1 . clock $end
$var reg 4 / present_state [3:0] $end
$scope module DP $end
$var wire 8 0 A [7:0] $end
$var wire 1 & RAin $end
$var wire 1 ' RAout $end
$var wire 1 ( RBin $end
$var wire 1 ) RBout $end
$var wire 1 * RZin $end
$var wire 1 + RZout $end
$var wire 8 1 RegisterAImmediate [7:0] $end
$var wire 1 - clear $end
$var wire 1 . clock $end
$var wire 8 2 Zregin [7:0] $end
$var wire 8 3 BusMuxOut [7:0] $end
$var wire 8 4 BusMuxInRZ [7:0] $end
$var wire 8 5 BusMuxInRB [7:0] $end
$var wire 8 6 BusMuxInRA [7:0] $end
$scope module RA $end
$var wire 8 7 BusMuxIn [7:0] $end
$var wire 8 8 BusMuxOut [7:0] $end
$var wire 1 - clear $end
$var wire 1 . clock $end
$var wire 1 & enable $end
$var parameter 32 9 DATA_WIDTH_IN $end
$var parameter 32 : DATA_WIDTH_OUT $end
$var parameter 8 ; INIT $end
$var reg 8 < q [7:0] $end
$upscope $end
$scope module RB $end
$var wire 8 = BusMuxIn [7:0] $end
$var wire 1 - clear $end
$var wire 1 . clock $end
$var wire 1 ( enable $end
$var wire 8 > BusMuxOut [7:0] $end
$var parameter 32 ? DATA_WIDTH_IN $end
$var parameter 32 @ DATA_WIDTH_OUT $end
$var parameter 8 A INIT $end
$var reg 8 B q [7:0] $end
$upscope $end
$scope module RZ $end
$var wire 8 C BusMuxIn [7:0] $end
$var wire 1 - clear $end
$var wire 1 . clock $end
$var wire 1 * enable $end
$var wire 8 D BusMuxOut [7:0] $end
$var parameter 32 E DATA_WIDTH_IN $end
$var parameter 32 F DATA_WIDTH_OUT $end
$var parameter 8 G INIT $end
$var reg 8 H q [7:0] $end
$upscope $end
$scope module add $end
$var wire 8 I A [7:0] $end
$var wire 8 J B [7:0] $end
$var reg 9 K LocalCarry [8:0] $end
$var reg 8 L Result [7:0] $end
$var integer 32 M i [31:0] $end
$upscope $end
$scope module bus $end
$var wire 8 N BusMuxInRA [7:0] $end
$var wire 8 O BusMuxInRB [7:0] $end
$var wire 8 P BusMuxInRZ [7:0] $end
$var wire 8 Q BusMuxOut [7:0] $end
$var wire 1 ' RAout $end
$var wire 1 ) RBout $end
$var wire 1 + RZout $end
$var reg 8 R q [7:0] $end
$upscope $end
$upscope $end
$upscope $end
$enddefinitions $end
$comment Show the parameter values. $end
$dumpall
b0 G
b1000 F
b1000 E
b0 A
b1000 @
b1000 ?
b0 ;
b1000 :
b1000 9
b1 $
b100 #
b11 "
b10 !
$end
#0
$dumpvars
bx R
bx Q
b0 P
b0 O
b0 N
b1000 M
bx L
b0 K
bx J
b0 I
b0 H
bx D
b0 C
b0 B
bx >
b0 =
b0 <
b0 8
b0 7
b0 6
b0 5
b0 4
bx 3
bx 2
b0 1
b0 0
b1 /
0.
1-
b0 ,
0+
0*
0)
0(
0'
0&
b0 %
$end
#1000
1.
#1500
0-
#2000
1&
b101 ,
b101 1
b101 8
b10 /
0.
#3000
b101 6
b101 7
b101 N
b101 <
1.
#3500
0&
b0 ,
b0 1
b0 8
#4000
b1010 K
b1010 2
b1010 D
b1010 L
b1000 M
b101 3
b101 >
b101 J
b101 Q
b101 R
1*
b101 %
b101 0
b101 I
1'
b11 /
0.
#5000
b1010 4
b1010 C
b1010 P
b1010 H
1.
#5500
0*
0'
#6000
b1111 2
b1111 D
b1111 L
b1000 M
b0 K
b1010 3
b1010 >
b1010 J
b1010 Q
b1010 R
1(
1+
b100 /
0.
#7000
b1010 5
b1010 =
b1010 O
b1010 B
1.
#7500
0(
0+
#8000
b101 /
0.
